burstlink/__init__.py
burstlink/_utils/__init__.py
burstlink/_utils/_probability_core.py
burstlink/_utils/_synthetic_data.py
burstlink/plotting/__init__.py
burstlink/plotting/_cluster_go.py
burstlink/plotting/_grn_visualization.py
burstlink/plotting/_plotting.py
burstlink/preprocessing/__init__.py
burstlink/preprocessing/_preprocess.py
burstlink/tools/__init__.py
burstlink/tools/_bursting_interactions.py
burstlink/tools/_downstream_analysis.py
burstlink-1.1.7.dist-info/licenses/LICENSE
burstlink-1.1.7.dist-info/METADATA
burstlink-1.1.7.dist-info/WHEEL
burstlink-1.1.7.dist-info/top_level.txt
burstlink-1.1.7.dist-info/RECORD
