Metadata-Version: 2.4
Name: burstlink
Version: 1.1.7
Summary: A user-friendly package for analyzing gene interactions and transcriptional bursting.
Home-page: https://github.com/LiyingZhou12/burstlink
Author: LiyingZhou
Author-email: zhouly68@mail2.sysu.edu.cn
License: MIT
Classifier: Programming Language :: Python :: 3
Classifier: License :: OSI Approved :: MIT License
Classifier: Operating System :: OS Independent
Classifier: Intended Audience :: Science/Research
Classifier: Topic :: Scientific/Engineering :: Bio-Informatics
Requires-Python: >=3.8
License-File: LICENSE
Requires-Dist: numpy>=1.21
Requires-Dist: scipy>=1.7
Requires-Dist: pandas>=1.3
Requires-Dist: matplotlib>=3.4
Requires-Dist: seaborn>=0.11
Requires-Dist: statsmodels>=0.12
Requires-Dist: scikit-learn>=1.0
Requires-Dist: umap-learn>=0.5
Requires-Dist: pyarrow>=6.0
Requires-Dist: joblib>=1.0
Requires-Dist: tqdm>=4.60
Requires-Dist: gseapy>=0.10.8
Dynamic: author
Dynamic: author-email
Dynamic: classifier
Dynamic: description
Dynamic: description-content-type
Dynamic: home-page
Dynamic: license
Dynamic: license-file
Dynamic: requires-dist
Dynamic: requires-python
Dynamic: summary
